curtely.py
curtely-0.0.2.dist-info/LICENSE
curtely-0.0.2.dist-info/METADATA
curtely-0.0.2.dist-info/WHEEL
curtely-0.0.2.dist-info/top_level.txt
curtely-0.0.2.dist-info/RECORD
