Metadata-Version: 2.1
Name: curtely
Version: 0.0.2
Summary: a 🧑‍💻Telegram API🧑‍💻 wrapper
Home-page: https://github.com/CURVoid/curtely
Author: VOID
License: APACHE 2.0
Keywords: telegram,api,curtely,messenger
Classifier: Operating System :: OS Independent
Classifier: License :: OSI Approved :: Apache Software License
Classifier: Programming Language :: Python :: 3
License-File: LICENSE
